chat_content/__init__.py
chat_content/core.py
chat_content-0.1.1.dist-info/LICENSE
chat_content-0.1.1.dist-info/METADATA
chat_content-0.1.1.dist-info/WHEEL
chat_content-0.1.1.dist-info/top_level.txt
chat_content-0.1.1.dist-info/RECORD
