Metadata-Version: 2.1
Name: chat-content
Version: 0.1.1
Summary: Fetch responses from GCP Discovery Engine (Agent Builder Chat App)
Home-page: https://github.com/Karthik-Sunil-K/chat-content
Author: Karthik Sunil K
Author-email: karthiksunil.me@gmail.com
License: UNKNOWN
Platform: UNKNOWN
Classifier: Programming Language :: Python :: 3
Classifier: License :: OSI Approved :: MIT License
Classifier: Operating System :: OS Independent
Requires-Python: >=3.7
License-File: LICENSE
Requires-Dist: google-api-core
Requires-Dist: google-cloud-discoveryengine
